drugintfinder/__init__.py
drugintfinder/__main__.py
drugintfinder/cli.py
drugintfinder/constants.py
drugintfinder/defaults.py
drugintfinder/finder.py
drugintfinder/models.py
drugintfinder/populate.py
drugintfinder/ranker.py
drugintfinder/utils.py
drugintfinder-0.3.3.dist-info/LICENSE
drugintfinder-0.3.3.dist-info/METADATA
drugintfinder-0.3.3.dist-info/WHEEL
drugintfinder-0.3.3.dist-info/entry_points.txt
drugintfinder-0.3.3.dist-info/top_level.txt
drugintfinder-0.3.3.dist-info/RECORD
