Metadata-Version: 2.1
Name: drugintfinder
Version: 0.3.3
Summary: DIF - Identification of druggable interactors in Knowledge Graphs
Home-page: https://github.com/e-bel/drugintfinder
Author: Bruce Schultz
Author-email: bruce.schultz@scai.fraunhofer.de
Maintainer: Bruce Schultz
Maintainer-email: bruce.schultz@scai.fraunhofer.de
License: MIT License
Project-URL: Bug Tracker, https://github.com/e-bel/drugintfinder/issues
Project-URL: Source Code, https://github.com/e-bel/drugintfinder
Project-URL: Documentation, https://druggable-interactor-finder.readthedocs.io/en/latest/
Keywords: Biological Expression Language,Graph Database,Biomedical Database
Classifier: Development Status :: 4 - Beta
Classifier: Environment :: Console
Classifier: Intended Audience :: Developers
Classifier: Intended Audience :: Science/Research
Classifier: License :: OSI Approved :: Apache Software License
Classifier: Operating System :: OS Independent
Classifier: Programming Language :: Python
Classifier: Programming Language :: Python :: 3.7
Classifier: Programming Language :: Python :: 3.8
Classifier: Programming Language :: Python :: 3.9
Classifier: Programming Language :: Python :: 3 :: Only
Classifier: Topic :: Scientific/Engineering :: Bio-Informatics
Requires-Python: >=3.7
License-File: LICENSE
Requires-Dist: click (>=8.0.1)
Requires-Dist: ebel-rest (>=1.0.17)
Requires-Dist: pandas (>=1.3.1)
Requires-Dist: matplotlib (>=3.4.2)
Requires-Dist: tqdm (>=4.61.2)
Requires-Dist: requests (>=2.26.0)
Requires-Dist: sqlalchemy (>=1.3.23)
Requires-Dist: sqlalchemy-utils (>=0.36.8)
Requires-Dist: openpyxl (>=3.0.7)
Provides-Extra: docs
Requires-Dist: sphinx ; extra == 'docs'
Requires-Dist: sphinx-rtd-theme ; extra == 'docs'
Requires-Dist: sphinx-click ; extra == 'docs'
Requires-Dist: sphinx-autodoc-typehints ; extra == 'docs'
